l0n0lacl/__init__.py
l0n0lacl/utils.py
l0n0lacl/动态库加载器.py
l0n0lacl/命令.py
l0n0lacl/张量.py
l0n0lacl/数据类型.py
l0n0lacl/数组.py
l0n0lacl/日志.py
l0n0lacl/标量.py
l0n0lacl/环境.py
l0n0lacl/算子运行器.py
l0n0lacl/设备.py
l0n0lacl/设备内存.py
l0n0lacl-2.1.0.dist-info/licenses/LICENSE
l0n0lacl-2.1.0.dist-info/METADATA
l0n0lacl-2.1.0.dist-info/WHEEL
l0n0lacl-2.1.0.dist-info/entry_points.txt
l0n0lacl-2.1.0.dist-info/top_level.txt
l0n0lacl-2.1.0.dist-info/RECORD
