Metadata-Version: 2.4
Name: l0n0lacl
Version: 2.1.0
Summary: 用于编写和调用ascendc算子
Requires-Python: >=3.11
License-File: LICENSE
Requires-Dist: colorama>=0.4.6
Requires-Dist: numpy>=1.24.0
Dynamic: license-file
